enum_with_dict/__init__.py
enum_with_dict/enum_with_dict.py
test/__init__.py
test/test_enum_with_dict.py
enum_with_dict-0.7.2.dist-info/LICENSE
enum_with_dict-0.7.2.dist-info/METADATA
enum_with_dict-0.7.2.dist-info/WHEEL
enum_with_dict-0.7.2.dist-info/top_level.txt
enum_with_dict-0.7.2.dist-info/RECORD
