Metadata-Version: 2.1
Name: enum_with_dict
Version: 0.7.2
Summary: Enum with to_dict method.
Home-page: https://github.com/jzombie/py-enum-with-dict
Author: Jeremy Harris
Author-email: jeremy.harris@zenosmosis.com
License: MIT
Keywords: enum python utilities enum-to-dict enum-with-dict
Classifier: Development Status :: 3 - Alpha
Classifier: Intended Audience :: Developers
Classifier: Topic :: Software Development :: Libraries
Classifier: License :: OSI Approved :: MIT License
Classifier: Programming Language :: Python :: 3
Classifier: Programming Language :: Python :: 3.7
Classifier: Programming Language :: Python :: 3.8
Classifier: Programming Language :: Python :: 3.9
Classifier: Programming Language :: Python :: 3.10
Classifier: Programming Language :: Python :: 3.11
Classifier: Programming Language :: Python :: 3.12
Classifier: Operating System :: OS Independent
Requires-Python: >=3.7
License-File: LICENSE
